{
  "description": "Custom ECL queries for Erythrocytes/RBC Count (LOINC 26453-1)",
  "queries": [
    {
      "id": "refined_query_v2",
      "name": "Refined Query V2 (Property-Specific: Number Concentration)",
      "description": "Uses Component = Erythrocyte AND Property = Number concentration (118550005) to separate RBC count from Hematocrit (which uses Volume fraction). This prevents cross-contamination between measurements that share the same Component.",
      "ecl": "<< 363787002 |Observable entity (observable entity)| : << 246093002 |Component (attribute)| = 41898006 |Erythrocyte (cell)|, << 704327008 |Direct site (attribute)| = << 119297000 |Blood specimen (specimen)|, << 370130000 |Property (attribute)| = << 118550005 |Number concentration (property) (qualifier value)|"
    }
  ]
}
